{
    "n_event": 895407,
    "clone_proportion": {
        "0": 0.9529075104223593,
        "1": 0.018096264458673007,
        "2": 0.008192776537826359,
        "3": 0.01856687650061672,
        "4": 0.00015576126989367628,
        "5": 2.6625858101483126e-06,
        "6": 0.00010517213950085835,
        "7": 0.0017819355534417582,
        "8": 0.00016042079506143584,
        "9": 7.987757430444938e-06,
        "10": 6.656464525370782e-07,
        "11": 1.1315989693130328e-05,
        "12": 6.656464525370782e-07,
        "13": 4.6595251677595475e-06,
        "14": 6.656464525370782e-07,
        "15": 1.9969393576112345e-06,
        "16": 1.9969393576112345e-06,
        "17": 6.656464525370782e-07
    },
    "clones": [
        {
            "id": 0,
            "fitness": 0,
            "ancestor": null,
            "dead_lineage": false,
            "size": 1523151,
            "tmb": 100
        },
        {
            "id": 1,
            "fitness": 0.6331991371692632,
            "ancestor": 0,
            "dead_lineage": false,
            "size": 28977,
            "tmb": 529
        },
        {
            "id": 2,
            "fitness": 0.6888547794356377,
            "ancestor": 0,
            "dead_lineage": false,
            "size": 13119,
            "tmb": 408
        },
        {
            "id": 3,
            "fitness": 1.561148070208622,
            "ancestor": 1,
            "dead_lineage": false,
            "size": 29641,
            "tmb": 613
        },
        {
            "id": 4,
            "fitness": 2.3628191698864245,
            "ancestor": 1,
            "dead_lineage": false,
            "size": 245,
            "tmb": 688
        },
        {
            "id": 5,
            "fitness": 0.9721488826982696,
            "ancestor": 2,
            "dead_lineage": false,
            "size": 5,
            "tmb": 711
        },
        {
            "id": 6,
            "fitness": 1.0310577291698186,
            "ancestor": 2,
            "dead_lineage": false,
            "size": 166,
            "tmb": 525
        },
        {
            "id": 7,
            "fitness": 2.835219534867955,
            "ancestor": 3,
            "dead_lineage": false,
            "size": 2867,
            "tmb": 811
        },
        {
            "id": 8,
            "fitness": 2.182648322601228,
            "ancestor": 3,
            "dead_lineage": false,
            "size": 251,
            "tmb": 1003
        },
        {
            "id": 9,
            "fitness": 2.9184052575731103,
            "ancestor": 4,
            "dead_lineage": false,
            "size": 12,
            "tmb": 796
        },
        {
            "id": 10,
            "fitness": 2.5652070034774552,
            "ancestor": 8,
            "dead_lineage": false,
            "size": 1,
            "tmb": 1188
        },
        {
            "id": 11,
            "fitness": 4.506555201855431,
            "ancestor": 7,
            "dead_lineage": false,
            "size": 18,
            "tmb": 1074
        },
        {
            "id": 12,
            "fitness": 3.270579437667035,
            "ancestor": 8,
            "dead_lineage": false,
            "size": 1,
            "tmb": 1258
        },
        {
            "id": 13,
            "fitness": 3.737720221596409,
            "ancestor": 7,
            "dead_lineage": false,
            "size": 9,
            "tmb": 1277
        },
        {
            "id": 14,
            "fitness": 6.369293140890776,
            "ancestor": 11,
            "dead_lineage": false,
            "size": 1,
            "tmb": 1159
        },
        {
            "id": 15,
            "fitness": 3.8663366353981123,
            "ancestor": 9,
            "dead_lineage": false,
            "size": 3,
            "tmb": 885
        },
        {
            "id": 16,
            "fitness": 2.4393878906612128,
            "ancestor": 4,
            "dead_lineage": false,
            "size": 3,
            "tmb": 1061
        },
        {
            "id": 17,
            "fitness": 1.53885055973234,
            "ancestor": 6,
            "dead_lineage": false,
            "size": 1,
            "tmb": 838
        }
    ]
}