{
    "n_event": 397030,
    "clone_proportion": {
        "0": 0.8027462337728324,
        "1": 0.1911330800135007,
        "2": 0.0056706624422499735,
        "3": 1.270228387063994e-05,
        "4": 0.00043550687556479797,
        "7": 1.8146119815199915e-06
    },
    "clones": [
        {
            "id": 0,
            "fitness": 0,
            "ancestor": null,
            "dead_lineage": false,
            "size": 507339,
            "tmb": 100
        },
        {
            "id": 1,
            "fitness": 0.9678880279913396,
            "ancestor": 0,
            "dead_lineage": false,
            "size": 120833,
            "tmb": 376
        },
        {
            "id": 2,
            "fitness": 1.3316348498998674,
            "ancestor": 0,
            "dead_lineage": false,
            "size": 3625,
            "tmb": 300
        },
        {
            "id": 3,
            "fitness": 1.8929932460807462,
            "ancestor": 1,
            "dead_lineage": false,
            "size": 7,
            "tmb": 658
        },
        {
            "id": 4,
            "fitness": 1.821660196248305,
            "ancestor": 1,
            "dead_lineage": false,
            "size": 268,
            "tmb": 978
        },
        {
            "id": 5,
            "fitness": 2.6705100480901347,
            "ancestor": 2,
            "dead_lineage": false,
            "size": 1,
            "tmb": 408
        },
        {
            "id": 6,
            "fitness": 1.7158314033262294,
            "ancestor": 2,
            "dead_lineage": false,
            "size": 1,
            "tmb": 452
        },
        {
            "id": 7,
            "fitness": 2.7991554758532495,
            "ancestor": 4,
            "dead_lineage": false,
            "size": 1,
            "tmb": 1267
        }
    ]
}