{
    "n_event": 299535,
    "clone_proportion": {
        "0": 0.4076660807191817,
        "1": 0.11331300213536567,
        "3": 0.002530585278954261,
        "4": 0.4718951665231292,
        "6": 0.0023418236730648988,
        "7": 0.0003627762113186178,
        "8": 0.0018905654589856423
    },
    "clones": [
        {
            "id": 0,
            "fitness": 0,
            "ancestor": null,
            "dead_lineage": false,
            "size": 173353,
            "tmb": 100
        },
        {
            "id": 1,
            "fitness": 1.3670594673168674,
            "ancestor": 0,
            "dead_lineage": false,
            "size": 48245,
            "tmb": 132
        },
        {
            "id": 2,
            "fitness": 1.2485132191539001,
            "ancestor": 0,
            "dead_lineage": true,
            "size": 1,
            "tmb": 174
        },
        {
            "id": 3,
            "fitness": 2.054485346744073,
            "ancestor": 1,
            "dead_lineage": false,
            "size": 1077,
            "tmb": 159
        },
        {
            "id": 4,
            "fitness": 3.5163200850896486,
            "ancestor": 1,
            "dead_lineage": false,
            "size": 201021,
            "tmb": 151
        },
        {
            "id": 5,
            "fitness": 4.0921020044260565,
            "ancestor": 4,
            "dead_lineage": true,
            "size": 1,
            "tmb": 169
        },
        {
            "id": 6,
            "fitness": 4.083277449531387,
            "ancestor": 4,
            "dead_lineage": false,
            "size": 1033,
            "tmb": 174
        },
        {
            "id": 7,
            "fitness": 2.8133358881972304,
            "ancestor": 3,
            "dead_lineage": false,
            "size": 156,
            "tmb": 165
        },
        {
            "id": 8,
            "fitness": 5.387295054983872,
            "ancestor": 6,
            "dead_lineage": false,
            "size": 829,
            "tmb": 198
        },
        {
            "id": 9,
            "fitness": 3.7143302424160547,
            "ancestor": 7,
            "dead_lineage": true,
            "size": 5,
            "tmb": 169
        },
        {
            "id": 10,
            "fitness": 3.306809006698443,
            "ancestor": 3,
            "dead_lineage": true,
            "size": 1,
            "tmb": 176
        },
        {
            "id": 11,
            "fitness": 6.446106400667279,
            "ancestor": 8,
            "dead_lineage": true,
            "size": 1,
            "tmb": 205
        },
        {
            "id": 12,
            "fitness": 5.072988948396017,
            "ancestor": 6,
            "dead_lineage": false,
            "size": 1,
            "tmb": 205
        },
        {
            "id": 13,
            "fitness": 6.842271056738805,
            "ancestor": 8,
            "dead_lineage": false,
            "size": 1,
            "tmb": 205
        }
    ]
}