{
    "n_event": 332412,
    "clone_proportion": {
        "0": 0.6130145678940426,
        "1": 0.010920719198745023,
        "2": 0.0689239065757335,
        "3": 0.1637670967822472,
        "4": 2.2885866105200083e-05,
        "5": 3.120799923436375e-05,
        "6": 0.10615504966232944,
        "7": 0.0017580506235358247,
        "8": 0.026352034553496752,
        "10": 0.0015458362287421512,
        "11": 0.007365087819309846,
        "12": 2.080533282290917e-06,
        "13": 4.1610665645818335e-05,
        "15": 3.120799923436375e-05,
        "16": 6.241599846872751e-06,
        "17": 5.825493190414567e-05,
        "18": 2.080533282290917e-06,
        "19": 2.080533282290917e-06
    },
    "clones": [
        {
            "id": 0,
            "fitness": 0,
            "ancestor": null,
            "dead_lineage": false,
            "size": 332583,
            "tmb": 100
        },
        {
            "id": 1,
            "fitness": 0.48755153496209214,
            "ancestor": 0,
            "dead_lineage": false,
            "size": 5891,
            "tmb": 177
        },
        {
            "id": 2,
            "fitness": 0.9884173922933256,
            "ancestor": 0,
            "dead_lineage": false,
            "size": 37311,
            "tmb": 183
        },
        {
            "id": 3,
            "fitness": 3.1912676368875927,
            "ancestor": 2,
            "dead_lineage": false,
            "size": 88721,
            "tmb": 285
        },
        {
            "id": 4,
            "fitness": 0.5726069013525256,
            "ancestor": 1,
            "dead_lineage": false,
            "size": 13,
            "tmb": 197
        },
        {
            "id": 5,
            "fitness": 1.2407551615905459,
            "ancestor": 1,
            "dead_lineage": false,
            "size": 15,
            "tmb": 254
        },
        {
            "id": 6,
            "fitness": 5.063069084169049,
            "ancestor": 3,
            "dead_lineage": false,
            "size": 57389,
            "tmb": 319
        },
        {
            "id": 7,
            "fitness": 2.336336375364542,
            "ancestor": 2,
            "dead_lineage": false,
            "size": 947,
            "tmb": 407
        },
        {
            "id": 8,
            "fitness": 3.780060526302175,
            "ancestor": 3,
            "dead_lineage": false,
            "size": 14283,
            "tmb": 324
        },
        {
            "id": 9,
            "fitness": 4.6651318314820225,
            "ancestor": 8,
            "dead_lineage": true,
            "size": 1,
            "tmb": 364
        },
        {
            "id": 10,
            "fitness": 6.1855940372726135,
            "ancestor": 6,
            "dead_lineage": false,
            "size": 847,
            "tmb": 434
        },
        {
            "id": 11,
            "fitness": 6.849722752820531,
            "ancestor": 6,
            "dead_lineage": false,
            "size": 3963,
            "tmb": 536
        },
        {
            "id": 12,
            "fitness": 4.318052898577715,
            "ancestor": 8,
            "dead_lineage": false,
            "size": 1,
            "tmb": 380
        },
        {
            "id": 13,
            "fitness": 4.405612377046383,
            "ancestor": 7,
            "dead_lineage": false,
            "size": 21,
            "tmb": 538
        },
        {
            "id": 14,
            "fitness": 7.904352444830702,
            "ancestor": 11,
            "dead_lineage": true,
            "size": 1,
            "tmb": 634
        },
        {
            "id": 15,
            "fitness": 8.024731218406219,
            "ancestor": 11,
            "dead_lineage": false,
            "size": 16,
            "tmb": 707
        },
        {
            "id": 16,
            "fitness": 3.437927624039684,
            "ancestor": 7,
            "dead_lineage": false,
            "size": 3,
            "tmb": 455
        },
        {
            "id": 17,
            "fitness": 7.301541963787827,
            "ancestor": 10,
            "dead_lineage": false,
            "size": 31,
            "tmb": 664
        },
        {
            "id": 18,
            "fitness": 6.576890197103348,
            "ancestor": 10,
            "dead_lineage": false,
            "size": 1,
            "tmb": 590
        },
        {
            "id": 19,
            "fitness": 8.962952673585157,
            "ancestor": 15,
            "dead_lineage": false,
            "size": 1,
            "tmb": 794
        }
    ]
}